riemannian_manifold/__init__.py
riemannian_manifold/riemannian_manifold.py
riemannian_manifold-0.2.dist-info/LICENSE
riemannian_manifold-0.2.dist-info/METADATA
riemannian_manifold-0.2.dist-info/WHEEL
riemannian_manifold-0.2.dist-info/top_level.txt
riemannian_manifold-0.2.dist-info/RECORD
