Metadata-Version: 2.1
Name: riemannian-manifold
Version: 0.2
Summary: A package for working with Riemannian manifolds in Python
Home-page: https://github.com/swittum/riemannian_manifold
Author: Simon Wittum
Author-email: simonwittum@gmx.de
Classifier: Programming Language :: Python :: 3
Classifier: License :: OSI Approved :: MIT License
Classifier: Operating System :: OS Independent
License-File: LICENSE
